news2play/__init__.py
news2play/__main__.py
news2play/__version__.py
news2play/_version.py
news2play/app.py
news2play/common/__init__.py
news2play/common/config.py
news2play/common/cursor_utils.py
news2play/common/utils.py
news2play/ssml/__init__.py
news2play/tts/__init__.py
news2play/web_downloader/__init__.py
news2play/web_downloader/clearning_tool.py
news2play/web_downloader/down_index.py
news2play/web_downloader/downloader.py
news2play/web_downloader/fid_spider.py
news2play/web_downloader/ts_tools.py
rest_api/__init__.py
rest_api/app.py
rest_api/equity_inquiry.py
tests/__init__.py
tests/test_ssml.py
news2play-0.5.12.dist-info/LICENSE
news2play-0.5.12.dist-info/METADATA
news2play-0.5.12.dist-info/WHEEL
news2play-0.5.12.dist-info/top_level.txt
news2play-0.5.12.dist-info/RECORD
