Metadata-Version: 2.1
Name: news2play
Version: 0.5.12
Summary: News for play.
Home-page: http://xxx.xxx
Author: xxx xxx
Author-email: xxx@xxx.xxx
License: Apache License, Version 2.0
Platform: UNKNOWN
Classifier: Development Status :: 5 - Production/Stable
Classifier: Intended Audience :: Developers
Classifier: Natural Language :: English
Classifier: License :: OSI Approved :: Apache Software License
Classifier: Programming Language :: Python
Classifier: Programming Language :: Python :: 3.6
Classifier: Programming Language :: Python :: 3.7
Requires-Python: >=3.0, !=3.1.*, !=3.2.*, !=3.3.*, !=3.4.*, !=3.5.*,
Requires-Dist: spacy
Requires-Dist: pydub
Requires-Dist: simpleaudio
Requires-Dist: pytz
Requires-Dist: colorlog
Requires-Dist: flask
Requires-Dist: flask-httpauth
Requires-Dist: nltk
Requires-Dist: textblob
Requires-Dist: schedule
Requires-Dist: boto3
Requires-Dist: xmltodict
